[
  {
    "source": "cbc",
    "logo": "https://upload.wikimedia.org/wikipedia/commons/c/cb/CBC_Logo_2020.svg",
    "headline": "Conservatives say a suspicious document was made to sway prisoners against them. We looked into it",
    "url": "https://www.cbc.ca/news/canada/alleged-prison-document-faked-1.7513211?cmp=rss",
    "category": "Politics"
  },
  {
    "source": "cbc",
    "logo": "https://upload.wikimedia.org/wikipedia/commons/c/cb/CBC_Logo_2020.svg",
    "headline": "Poilievre says costed platform is coming 'soon,' becoming last leader to release a plan",
    "url": "https://www.cbc.ca/news/politics/poilievre-no-platform-yet-1.7514480?cmp=rss",
    "category": "Politics"
  },
  {
    "source": "cbc",
    "logo": "https://upload.wikimedia.org/wikipedia/commons/c/cb/CBC_Logo_2020.svg",
    "headline": "Elections Canada announces record turnout on 1st day of advance voting",
    "url": "https://www.cbc.ca/news/politics/elections-canada-record-turnout-first-day-advance-voting-1.7514390?cmp=rss",
    "category": "Politics"
  },
  {
    "source": "cbc",
    "logo": "https://upload.wikimedia.org/wikipedia/commons/c/cb/CBC_Logo_2020.svg",
    "headline": "NDP wealth tax would raise $94.5B, pay for worker tax cut and health-care improvements",
    "url": "https://www.cbc.ca/news/politics/ndp-wealth-tax-would-raise-94-5b-pay-for-worker-tax-cut-and-health-care-improvements-1.7514340?cmp=rss",
    "category": "Politics"
  },
  {
    "source": "cbc",
    "logo": "https://upload.wikimedia.org/wikipedia/commons/c/cb/CBC_Logo_2020.svg",
    "headline": "Liberal platform promises $130B in new measures over 4 years, adding $225B to federal debt",
    "url": "https://www.cbc.ca/news/politics/liberal-costed-platform-1.7514272?cmp=rss",
    "category": "Politics"
  },
  {
    "source": "cbc",
    "logo": "https://upload.wikimedia.org/wikipedia/commons/c/cb/CBC_Logo_2020.svg",
    "headline": "Trump is demanding universities change policies or face defunding. Would Poilievre do the same?",
    "url": "https://www.cbc.ca/news/politics/poilievre-trump-universities-defund-1.7512547?cmp=rss",
    "category": "Politics"
  },
  {
    "source": "cbc",
    "logo": "https://upload.wikimedia.org/wikipedia/commons/c/cb/CBC_Logo_2020.svg",
    "headline": "Rebel News owner Ezra Levant was 'mentor' to Poilievre, says author",
    "url": "https://www.cbc.ca/news/politics/levant-rebel-poilievre-1.7514216?cmp=rss",
    "category": "Politics"
  },
  {
    "source": "cbc",
    "logo": "https://upload.wikimedia.org/wikipedia/commons/c/cb/CBC_Logo_2020.svg",
    "headline": "As foreign actors work to influence Canada's election, how safe is your vote?",
    "url": "https://www.cbc.ca/news/politics/how-safe-is-your-vote-podcast-1.7513127?cmp=rss",
    "category": "Politics"
  },
  {
    "source": "cbc",
    "logo": "https://upload.wikimedia.org/wikipedia/commons/c/cb/CBC_Logo_2020.svg",
    "headline": "How will the parties pay for their promises? Why costed platforms are important",
    "url": "https://www.cbc.ca/news/politics/costed-platforms-1.7514108?cmp=rss",
    "category": "Politics"
  },
  {
    "source": "cbc",
    "logo": "https://upload.wikimedia.org/wikipedia/commons/c/cb/CBC_Logo_2020.svg",
    "headline": "From salt in food to transfer payments: Here's what Ottawa has power over when it comes to your health",
    "url": "https://www.cbc.ca/radio/the-dose/federal-government-health-care-1.7513495?cmp=rss",
    "category": "Politics"
  },
  {
    "source": "cbc",
    "logo": "https://upload.wikimedia.org/wikipedia/commons/c/cb/CBC_Logo_2020.svg",
    "headline": "Mark Carney and Pierre Poilievre see very different threats to Canada",
    "url": "https://www.cbc.ca/news/politics/carney-poilievre-debate-trump-analysis-1.7514109?cmp=rss",
    "category": "Politics"
  },
  {
    "source": "cbc",
    "logo": "https://upload.wikimedia.org/wikipedia/commons/c/cb/CBC_Logo_2020.svg",
    "headline": "Long lines at polling stations as Canadians turn up for advance voting",
    "url": "https://www.cbc.ca/news/canada/long-lines-advance-voting-1.7514157?cmp=rss",
    "category": "Politics"
  },
  {
    "source": "cbc",
    "logo": "https://upload.wikimedia.org/wikipedia/commons/c/cb/CBC_Logo_2020.svg",
    "headline": "Poilievre promises to scrap single-use plastics ban and bring back the plastic straw",
    "url": "https://www.cbc.ca/news/politics/poilievre-scrap-plastics-ban-1.7514037?cmp=rss",
    "category": "Politics"
  },
  {
    "source": "cbc",
    "logo": "https://upload.wikimedia.org/wikipedia/commons/c/cb/CBC_Logo_2020.svg",
    "headline": "Leaders' debate likely won't influence most people's votes, Vote Compass data suggests",
    "url": "https://www.cbc.ca/news/politics/english-debate-vote-compass-1.7514070?cmp=rss",
    "category": "Politics"
  },
  {
    "source": "cbc",
    "logo": "https://upload.wikimedia.org/wikipedia/commons/c/cb/CBC_Logo_2020.svg",
    "headline": "5 things federal party leaders keep getting wrong",
    "url": "https://www.cbc.ca/news/politics/election-2025-fact-checking-1.7513874?cmp=rss",
    "category": "Politics"
  },
  {
    "source": "cbc",
    "logo": "https://upload.wikimedia.org/wikipedia/commons/c/cb/CBC_Logo_2020.svg",
    "headline": "6 big moments and takeaways from the final leaders' debate",
    "url": "https://www.cbc.ca/news/politics/key-moments-english-leadership-debate-1.7513787?cmp=rss",
    "category": "Politics"
  },
  {
    "source": "cbc",
    "logo": "https://upload.wikimedia.org/wikipedia/commons/c/cb/CBC_Logo_2020.svg",
    "headline": "Election campaign, debates will give voters something to chew on this long weekend",
    "url": "https://www.cbc.ca/news/politics/election-long-weekend-1.7512092?cmp=rss",
    "category": "Politics"
  },
  {
    "source": "cbc",
    "logo": "https://upload.wikimedia.org/wikipedia/commons/c/cb/CBC_Logo_2020.svg",
    "headline": "I want to buy Canadian, but can't always afford to. Cost of living is my election priority",
    "url": "https://www.cbc.ca/news/canada/prince-edward-island/pei-first-person-crystal-maccormac-1.7510022?cmp=rss",
    "category": "Politics"
  },
  {
    "source": "cbc",
    "logo": "https://upload.wikimedia.org/wikipedia/commons/c/cb/CBC_Logo_2020.svg",
    "headline": "Fractious debate sees leaders trade blows over Trump, Trudeau and the cost of living",
    "url": "https://www.cbc.ca/news/politics/english-leaders-debate-election-2025-1.7513834?cmp=rss",
    "category": "Politics"
  },
  {
    "source": "cbc",
    "logo": "https://upload.wikimedia.org/wikipedia/commons/c/cb/CBC_Logo_2020.svg",
    "headline": "Advance polls open across the country Friday morning",
    "url": "https://www.cbc.ca/news/politics/advance-polling-begins-1.7513017?cmp=rss",
    "category": "Politics"
  }
]