[
  {
    "source": "weather.gc",
    "logo": "https://cdn.shopify.com/s/files/1/0649/5997/1534/files/images.png?v=1743940410",
    "headline": "No watches or warnings in effect, Ottawa",
    "url": "https://weather.gc.ca/index_e.html",
    "category": "Weather"
  },
  {
    "source": "weather.gc",
    "logo": "https://cdn.shopify.com/s/files/1/0649/5997/1534/files/images.png?v=1743940410",
    "headline": "Current Conditions: Light Rain, 12.1°C",
    "url": "https://weather.gc.ca/en/location/index.html?coords=45.403,-75.687",
    "category": "Weather"
  },
  {
    "source": "weather.gc",
    "logo": "https://cdn.shopify.com/s/files/1/0649/5997/1534/files/images.png?v=1743940410",
    "headline": "Sunday: Showers. High 13.",
    "url": "https://weather.gc.ca/en/location/index.html?coords=45.403,-75.687",
    "category": "Weather"
  },
  {
    "source": "weather.gc",
    "logo": "https://cdn.shopify.com/s/files/1/0649/5997/1534/files/images.png?v=1743940410",
    "headline": "Sunday night: Chance of showers. Low plus 5. POP 30%",
    "url": "https://weather.gc.ca/en/location/index.html?coords=45.403,-75.687",
    "category": "Weather"
  },
  {
    "source": "weather.gc",
    "logo": "https://cdn.shopify.com/s/files/1/0649/5997/1534/files/images.png?v=1743940410",
    "headline": "Monday: Overcast. High 15.",
    "url": "https://weather.gc.ca/en/location/index.html?coords=45.403,-75.687",
    "category": "Weather"
  },
  {
    "source": "weather.gc",
    "logo": "https://cdn.shopify.com/s/files/1/0649/5997/1534/files/images.png?v=1743940410",
    "headline": "Monday night: Cloudy periods. Low 6.",
    "url": "https://weather.gc.ca/en/location/index.html?coords=45.403,-75.687",
    "category": "Weather"
  },
  {
    "source": "weather.gc",
    "logo": "https://cdn.shopify.com/s/files/1/0649/5997/1534/files/images.png?v=1743940410",
    "headline": "Tuesday: A mix of sun and cloud. High 13.",
    "url": "https://weather.gc.ca/en/location/index.html?coords=45.403,-75.687",
    "category": "Weather"
  },
  {
    "source": "weather.gc",
    "logo": "https://cdn.shopify.com/s/files/1/0649/5997/1534/files/images.png?v=1743940410",
    "headline": "Tuesday night: Cloudy. Low 8.",
    "url": "https://weather.gc.ca/en/location/index.html?coords=45.403,-75.687",
    "category": "Weather"
  },
  {
    "source": "weather.gc",
    "logo": "https://cdn.shopify.com/s/files/1/0649/5997/1534/files/images.png?v=1743940410",
    "headline": "Wednesday: Chance of showers. High 12. POP 40%",
    "url": "https://weather.gc.ca/en/location/index.html?coords=45.403,-75.687",
    "category": "Weather"
  },
  {
    "source": "weather.gc",
    "logo": "https://cdn.shopify.com/s/files/1/0649/5997/1534/files/images.png?v=1743940410",
    "headline": "Wednesday night: Chance of showers. Low 9. POP 40%",
    "url": "https://weather.gc.ca/en/location/index.html?coords=45.403,-75.687",
    "category": "Weather"
  },
  {
    "source": "weather.gc",
    "logo": "https://cdn.shopify.com/s/files/1/0649/5997/1534/files/images.png?v=1743940410",
    "headline": "Thursday: Chance of showers. High 11. POP 60%",
    "url": "https://weather.gc.ca/en/location/index.html?coords=45.403,-75.687",
    "category": "Weather"
  },
  {
    "source": "weather.gc",
    "logo": "https://cdn.shopify.com/s/files/1/0649/5997/1534/files/images.png?v=1743940410",
    "headline": "Thursday night: Chance of showers. Low 8. POP 30%",
    "url": "https://weather.gc.ca/en/location/index.html?coords=45.403,-75.687",
    "category": "Weather"
  },
  {
    "source": "weather.gc",
    "logo": "https://cdn.shopify.com/s/files/1/0649/5997/1534/files/images.png?v=1743940410",
    "headline": "Friday: Chance of showers. High 12. POP 30%",
    "url": "https://weather.gc.ca/en/location/index.html?coords=45.403,-75.687",
    "category": "Weather"
  },
  {
    "source": "weather.gc",
    "logo": "https://cdn.shopify.com/s/files/1/0649/5997/1534/files/images.png?v=1743940410",
    "headline": "Friday night: Chance of showers. Low 7. POP 70%",
    "url": "https://weather.gc.ca/en/location/index.html?coords=45.403,-75.687",
    "category": "Weather"
  },
  {
    "source": "weather.gc",
    "logo": "https://cdn.shopify.com/s/files/1/0649/5997/1534/files/images.png?v=1743940410",
    "headline": "Saturday: Chance of showers. High 14. POP 40%",
    "url": "https://weather.gc.ca/en/location/index.html?coords=45.403,-75.687",
    "category": "Weather"
  },
  {
    "source": "weather.gc",
    "logo": "https://cdn.shopify.com/s/files/1/0649/5997/1534/files/images.png?v=1743940410",
    "headline": "Notice",
    "url": "https://weather.gc.ca/canada_e.html",
    "category": "Weather"
  }
]